google_calendar/__init__.py
google_calendar/google_calendar.py
google_calendar/models/__init__.py
google_calendar/models/acl.py
google_calendar/models/attachment.py
google_calendar/models/attendee.py
google_calendar/models/calendar_list.py
google_calendar/models/calendars.py
google_calendar/models/channels.py
google_calendar/models/colors.py
google_calendar/models/conference_data.py
google_calendar/models/conference_properties.py
google_calendar/models/conference_solution.py
google_calendar/models/creator.py
google_calendar/models/entry_point.py
google_calendar/models/event.py
google_calendar/models/event_time.py
google_calendar/models/focus_time_properties.py
google_calendar/models/freebusy.py
google_calendar/models/office_location.py
google_calendar/models/organizer.py
google_calendar/models/out_of_office_properties.py
google_calendar/models/person.py
google_calendar/models/reminder.py
google_calendar/models/reminders.py
google_calendar/models/resource.py
google_calendar/models/settings.py
google_calendar/models/source.py
google_calendar/models/working_location_properties.py
google_calendar/resources/__init__.py
google_calendar/resources/calendar.py
google_calendar/resources/event.py
google_calendar/resources/resource.py
google_calendar/schemas/__init__.py
google_calendar/schemas/attendee.py
google_calendar/schemas/calendar.py
google_calendar/schemas/calendar_events.py
google_calendar/schemas/calendar_request.py
google_calendar/schemas/default_reminder.py
google_calendar/schemas/event.py
google_calendar/schemas/event_instance.py
google_calendar/schemas/event_time.py
google_calendar/schemas/reminder.py
google_calendar/schemas/reminders.py
oryks_google_calendar-0.3.1.dist-info/LICENSE
oryks_google_calendar-0.3.1.dist-info/METADATA
oryks_google_calendar-0.3.1.dist-info/WHEEL
oryks_google_calendar-0.3.1.dist-info/top_level.txt
oryks_google_calendar-0.3.1.dist-info/RECORD
